framex/__init__.py
framex/_dicts/__init__.py
framex/_dicts/_all.py
framex/_dicts/_constants.py
framex/_dicts/_github.py
framex/_dicts/_local.py
framex/cli/_cli.py
framex/cli/_entry.py
framex/datasets/__init__.py
framex/datasets/core.py
framex/datasets/get_url.py
framex/datasets/info.py
framex/utils/__init__.py
framex/utils/_colors.py
framex/utils/_exceptions.py
framex-1.0.2.dist-info/LICENSE
framex-1.0.2.dist-info/METADATA
framex-1.0.2.dist-info/WHEEL
framex-1.0.2.dist-info/entry_points.txt
framex-1.0.2.dist-info/RECORD
