Metadata-Version: 2.3
Name: framex
Version: 1.0.2
Summary: dataframe operations
License: Apache-2.0
Author: Zaf4
Author-email: zafermolbio@gmail.com
Requires-Python: >=3.8,<4.0
Classifier: License :: OSI Approved :: Apache Software License
Classifier: Programming Language :: Python :: 3
Classifier: Programming Language :: Python :: 3.8
Classifier: Programming Language :: Python :: 3.9
Classifier: Programming Language :: Python :: 3.10
Classifier: Programming Language :: Python :: 3.11
Classifier: Programming Language :: Python :: 3.12
Classifier: Programming Language :: Python :: 3.13
Requires-Dist: polars (>=1.7.1,<2.0.0)
Requires-Dist: rich-argparse (>=1.7.0,<2.0.0)
